README.rst
objproxies.py
setup.py
objproxies.egg-info/PKG-INFO
objproxies.egg-info/SOURCES.txt
objproxies.egg-info/dependency_links.txt
objproxies.egg-info/top_level.txt