Metadata-Version: 1.1
Name: objproxies
Version: 0.9.4
Summary: General purpose proxy and wrapper types
Home-page: http://github.com/soulrebel/objproxies
Author: Andrea Ratto
Author-email: andrearatto_liste@yahoo.it
License: PSF or ZPL
Keywords: proxy pattern lazy wrapper
Platform: UNKNOWN
Classifier: Development Status :: 5 - Production/Stable
Classifier: Intended Audience :: Developers
Classifier: License :: OSI Approved :: Zope Public License
Classifier: License :: OSI Approved :: Python Software Foundation License
Classifier: Operating System :: OS Independent
Classifier: Programming Language :: Python
Classifier: Topic :: Software Development :: Libraries
